omz_tools/_common.py
omz_tools/_concurrency.py
omz_tools/_configuration.py
omz_tools/_reporting.py
omz_tools/_version.py
omz_tools/models.py
omz_tools/omz_converter.py
omz_tools/omz_data_downloader.py
omz_tools/omz_downloader.py
omz_tools/omz_info_dumper.py
omz_tools/data/dataset_definitions.yml
omz_tools/data/datasets.md
omz_tools/data/dataset_classes/aclnet_53cl.txt
omz_tools/data/dataset_classes/cityscapes_19cl.txt
omz_tools/data/dataset_classes/cityscapes_19cl_bkgr.txt
omz_tools/data/dataset_classes/coco_80cl.txt
omz_tools/data/dataset_classes/coco_80cl_bkgr.txt
omz_tools/data/dataset_classes/coco_91cl.txt
omz_tools/data/dataset_classes/coco_91cl_bkgr.txt
omz_tools/data/dataset_classes/common_sign_language12.json
omz_tools/data/dataset_classes/gnhk.txt
omz_tools/data/dataset_classes/imagenet_2012.txt
omz_tools/data/dataset_classes/imagenet_2015.txt
omz_tools/data/dataset_classes/jester27.json
omz_tools/data/dataset_classes/kondate_nakayosi.txt
omz_tools/data/dataset_classes/msasl100.json
omz_tools/data/dataset_classes/scut_ept.txt
omz_tools/data/dataset_classes/sygdata_4cl.txt
omz_tools/data/dataset_classes/voc_20cl.txt
omz_tools/data/dataset_classes/voc_20cl_bkgr.txt
omz_tools/data/palettes/ade20k_150cl_colors.txt
omz_tools/data/palettes/camvid_12cl_colors.txt
omz_tools/data/palettes/cityscapes_20cl_colors.txt
omz_tools/data/palettes/pascal_voc_21cl_colors.txt
omz_tools/download_engine/__init__.py
omz_tools/download_engine/base.py
omz_tools/download_engine/cache.py
omz_tools/download_engine/downloader.py
omz_tools/download_engine/file_source.py
omz_tools/download_engine/postprocessing.py
omz_tools/download_engine/validation.py
omz_tools/internal_scripts/pytorch_to_onnx.py
omz_tools/models/intel/action-recognition-0001/accuracy-check.yml
omz_tools/models/intel/action-recognition-0001/composite-model.yml
omz_tools/models/intel/action-recognition-0001/action-recognition-0001-decoder/model.yml
openvino_dev-2024.4.0.dist-info/LICENSE
openvino_dev-2024.4.0.dist-info/METADATA
openvino_dev-2024.4.0.dist-info/WHEEL
openvino_dev-2024.4.0.dist-info/dev-third-party-programs.txt
openvino_dev-2024.4.0.dist-info/entry_points.txt
openvino_dev-2024.4.0.dist-info/omz-third-party-programs.txt
openvino_dev-2024.4.0.dist-info/readme.txt
openvino_dev-2024.4.0.dist-info/top_level.txt
openvino_dev-2024.4.0.dist-info/RECORD
