Metadata-Version: 2.1
Name: openvino-dev
Version: 2024.4.0
Summary: OpenVINO(TM) Development Tools
Home-page: https://docs.openvino.ai/2023.0/index.html
Download-URL: https://github.com/openvinotoolkit/openvino/tags
Author: Intel® Corporation
Author-email: openvino_pushbot@intel.com
License: OSI Approved :: Apache Software License
Classifier: Programming Language :: Python :: 3
Classifier: Operating System :: OS Independent
License-File: readme.txt
License-File: LICENSE
License-File: dev-third-party-programs.txt
License-File: omz-third-party-programs.txt
Requires-Dist: defusedxml>=0.7.1
Requires-Dist: networkx<=3.1.0
Requires-Dist: numpy<2.0.0,>=1.16.6
Requires-Dist: openvino-telemetry>=2023.2.1
Requires-Dist: packaging
Requires-Dist: pyyaml>=5.4.1
Requires-Dist: requests>=2.25.1
Requires-Dist: openvino==2024.4.0
Requires-Dist: importlib-metadata; python_version < "3.8" and sys_platform == "win32"
Provides-Extra: caffe
Requires-Dist: defusedxml>=0.7.1; extra == "caffe"
Requires-Dist: fastjsonschema<2.18,>=2.15.1; extra == "caffe"
Requires-Dist: protobuf<4.0.0,>=3.18.1; extra == "caffe"
Requires-Dist: requests>=2.25.1; extra == "caffe"
Requires-Dist: numpy<1.27,>=1.16.6; extra == "caffe"
Requires-Dist: networkx<=3.1.0; extra == "caffe"
Provides-Extra: kaldi
Requires-Dist: defusedxml>=0.7.1; extra == "kaldi"
Requires-Dist: fastjsonschema<2.18,>=2.15.1; extra == "kaldi"
Requires-Dist: requests>=2.25.1; extra == "kaldi"
Requires-Dist: numpy<1.27,>=1.16.6; extra == "kaldi"
Requires-Dist: networkx<=3.1.0; extra == "kaldi"
Provides-Extra: mxnet
Requires-Dist: defusedxml>=0.7.1; extra == "mxnet"
Requires-Dist: urllib3>=1.26.4; extra == "mxnet"
Requires-Dist: fastjsonschema<2.18,>=2.15.1; extra == "mxnet"
Requires-Dist: requests>=2.25.1; extra == "mxnet"
Requires-Dist: numpy<1.27,>=1.16.6; extra == "mxnet"
Requires-Dist: networkx<=3.1.0; extra == "mxnet"
Requires-Dist: mxnet<=1.9.1,>=1.7.0.post2; sys_platform != "win32" and extra == "mxnet"
Requires-Dist: mxnet~=1.2.0; sys_platform == "win32" and extra == "mxnet"
Provides-Extra: onnx
Requires-Dist: defusedxml>=0.7.1; extra == "onnx"
Requires-Dist: fastjsonschema<2.18,>=2.15.1; extra == "onnx"
Requires-Dist: protobuf<4.0.0,>=3.18.1; extra == "onnx"
Requires-Dist: onnx<=1.16.0,>=1.8.1; extra == "onnx"
Requires-Dist: requests>=2.25.1; extra == "onnx"
Requires-Dist: numpy<1.27,>=1.16.6; extra == "onnx"
Requires-Dist: networkx<=3.1.0; extra == "onnx"
Provides-Extra: pytorch
Requires-Dist: torch>=1.8.1; extra == "pytorch"
Requires-Dist: yacs>=0.1.8; extra == "pytorch"
Requires-Dist: onnx>=1.13; extra == "pytorch"
Requires-Dist: torchvision>=0.17; extra == "pytorch"
Requires-Dist: scipy>=1.5.4; extra == "pytorch"
Requires-Dist: mpmath<1.4; extra == "pytorch"
Provides-Extra: tensorflow
Requires-Dist: h5py<3.11.0,>=3.1.0; extra == "tensorflow"
Requires-Dist: defusedxml>=0.7.1; extra == "tensorflow"
Requires-Dist: fastjsonschema<2.18,>=2.15.1; extra == "tensorflow"
Requires-Dist: tensorflow<2.18.0,>=1.15.5; extra == "tensorflow"
Requires-Dist: requests>=2.25.1; extra == "tensorflow"
Requires-Dist: numpy<1.27,>=1.16.6; extra == "tensorflow"
Requires-Dist: networkx<=3.1.0; extra == "tensorflow"
Provides-Extra: tensorflow2
Requires-Dist: h5py<3.11.0,>=3.1.0; extra == "tensorflow2"
Requires-Dist: defusedxml>=0.7.1; extra == "tensorflow2"
Requires-Dist: fastjsonschema<2.18,>=2.15.1; extra == "tensorflow2"
Requires-Dist: tensorflow<2.18.0,>=2.5; extra == "tensorflow2"
Requires-Dist: requests>=2.25.1; extra == "tensorflow2"
Requires-Dist: numpy<1.27,>=1.16.6; extra == "tensorflow2"
Requires-Dist: networkx<=3.1.0; extra == "tensorflow2"
